lmfit/__init__.py
lmfit/_ampgo.py
lmfit/confidence.py
lmfit/jsonutils.py
lmfit/lineshapes.py
lmfit/minimizer.py
lmfit/model.py
lmfit/models.py
lmfit/parameter.py
lmfit/printfuncs.py
lmfit/version.py
lmfit-1.3.2.dist-info/AUTHORS.txt
lmfit-1.3.2.dist-info/LICENSE
lmfit-1.3.2.dist-info/METADATA
lmfit-1.3.2.dist-info/WHEEL
lmfit-1.3.2.dist-info/top_level.txt
lmfit-1.3.2.dist-info/RECORD
