Metadata-Version: 2.1
Name: lmfit
Version: 1.3.2
Summary: Least-Squares Minimization with Bounds and Constraints
Author-email: LMFit Development Team <matt.newville@gmail.com>
License: BSD-3
Project-URL: Homepage, https://lmfit.github.io//lmfit-py/
Project-URL: Documentation, https://lmfit.github.io/lmfit-py/
Project-URL: Changelog, https://lmfit.github.io/lmfit-py/whatsnew.html
Keywords: curve-fitting, least-squares minimization
Classifier: Development Status :: 5 - Production/Stable
Classifier: Intended Audience :: Science/Research
Classifier: Topic :: Scientific/Engineering
Classifier: License :: OSI Approved :: BSD License
Classifier: Operating System :: OS Independent
Classifier: Programming Language :: Python :: 3
Classifier: Programming Language :: Python :: 3 :: Only
Classifier: Programming Language :: Python :: 3.8
Classifier: Programming Language :: Python :: 3.9
Classifier: Programming Language :: Python :: 3.10
Classifier: Programming Language :: Python :: 3.11
Classifier: Programming Language :: Python :: 3.12
Classifier: Programming Language :: Python :: Implementation :: CPython
Classifier: Programming Language :: Python :: Implementation :: PyPy
Requires-Python: >=3.8
License-File: LICENSE
License-File: AUTHORS.txt
Requires-Dist: asteval>=1.0
Requires-Dist: numpy>=1.19
Requires-Dist: scipy>=1.6
Requires-Dist: uncertainties>=3.2.2
Requires-Dist: dill>=0.3.4
Provides-Extra: dev
Requires-Dist: build; extra == "dev"
Requires-Dist: check-wheel-contents; extra == "dev"
Requires-Dist: flake8-pyproject; extra == "dev"
Requires-Dist: pre-commit; extra == "dev"
Requires-Dist: twine; extra == "dev"
Provides-Extra: doc
Requires-Dist: cairosvg; extra == "doc"
Requires-Dist: corner; extra == "doc"
Requires-Dist: emcee>=3.0.0; extra == "doc"
Requires-Dist: ipykernel; extra == "doc"
Requires-Dist: jupyter_sphinx>=0.2.4; extra == "doc"
Requires-Dist: matplotlib; extra == "doc"
Requires-Dist: numdifftools; extra == "doc"
Requires-Dist: pandas; extra == "doc"
Requires-Dist: numexpr; extra == "doc"
Requires-Dist: Pillow; extra == "doc"
Requires-Dist: pycairo; platform_system == "Windows" and extra == "doc"
Requires-Dist: Sphinx; extra == "doc"
Requires-Dist: sphinx-gallery>=0.10; extra == "doc"
Requires-Dist: sphinxcontrib-svg2pdfconverter; extra == "doc"
Requires-Dist: sympy; extra == "doc"
Provides-Extra: test
Requires-Dist: coverage; extra == "test"
Requires-Dist: flaky; extra == "test"
Requires-Dist: pytest; extra == "test"
Requires-Dist: pytest-cov; extra == "test"
Provides-Extra: all
Requires-Dist: lmfit[dev,doc,test]; extra == "all"
